{
  "noindex": true,
  "title": "Create and Modify Tables",
  "description": "Create and modify tables using the built-in SQL shell.",
  "details": {
    "steps": [
      {
        "title": "Start CockroachDB",
        "text": "step1.md",
        "foreground": "foreground.sh"
      },
      {
        "title": "Load a Sample Dataset",
        "text": "step2.md"
      },
      {
        "title": "Connect with the SQL shell",
        "text": "step3.md"
      }
    ]
  },
  "environment": {
    "hideintro": true,
    "hidefinish": true,
    "uilayout": "terminal"
  },
  "backend": {
    "imageid": "ubuntu:1804"
  }
}
